<?xml version="1.0" ?>
<ClassField FieldClassName="DataSessionData" FieldName="Data" ReturnType="4" ReturnClassName="ICLBLOB" ClientAccessType="1" SupportsScenario="0" DBFieldName="Data" ToBeReleased="0" DBSynchronizationIsAllowed="1" DBReturnType="4" Length="0" DBIsPrimary="0" DBIsMasterData="0" SubReturnType="0" OptionIsMultiSelect="" GUITag="" ProcessTag="" ActionTag="" FieldType_RO="None">
	<DefaultValueExpression/>
	<DBDefaultValue/>
	<InitialValueExpStr/>
	<EditMask/>
	<DisplayFormat/>
	<OnChangeExpStr/>
	<OptionsExpStr/>
	<VisibilityConditionExpStr/>
	<ErrorExpression/>
	<ToolTip/>
	<WEBDisplayFormat/>
	<WEBEditMask/>
	<ObjectToolTip/>
	<ReleaseContextNames/>
</ClassField>
